py_wa_adb/__init__.py
py_wa_adb/cli.py
py_wa_adb/enums.py
py_wa_adb/wa_adb.py
py_wa_adb/wa_sqlite.py
py_wa_adb-0.1.2.dist-info/METADATA
py_wa_adb-0.1.2.dist-info/WHEEL
py_wa_adb-0.1.2.dist-info/entry_points.txt
py_wa_adb-0.1.2.dist-info/top_level.txt
py_wa_adb-0.1.2.dist-info/RECORD
